{
  "main": {
    "id": "2a260c27fd573bf1",
    "type": "split",
    "children": [
      {
        "id": "2e4848325ff6645f",
        "type": "tabs",
        "children": [
          {
            "id": "7c01c466821cbbb0",
            "type": "leaf",
            "state": {
              "type": "empty",
              "state": {},
              "icon": "lucide-file",
              "title": "Nova aba"
            }
          }
        ]
      }
    ],
    "direction": "vertical"
  },
  "left": {
    "id": "411f6293de2d2a81",
    "type": "split",
    "children": [
      {
        "id": "a1069ab63898f423",
        "type": "tabs",
        "children": [
          {
            "id": "f13b409cc3ecdea9",
            "type": "leaf",
            "state": {
              "type": "file-explorer",
              "state": {
                "sortOrder": "alphabetical",
                "autoReveal": false
              },
              "icon": "lucide-folder-closed",
              "title": "Explorador de arquivos"
            }
          },
          {
            "id": "1e1247dd89d7d6f5",
            "type": "leaf",
            "state": {
              "type": "search",
              "state": {
                "query": "Declarando",
                "matchingCase": false,
                "explainSearch": false,
                "collapseAll": false,
                "extraContext": false,
                "sortOrder": "alphabetical"
              },
              "icon": "lucide-search",
              "title": "Procurar"
            }
          },
          {
            "id": "00807e2344381573",
            "type": "leaf",
            "state": {
              "type": "bookmarks",
              "state": {},
              "icon": "lucide-bookmark",
              "title": "Marcadores"
            }
          }
        ]
      }
    ],
    "direction": "horizontal",
    "width": 306.5,
    "collapsed": true
  },
  "right": {
    "id": "fae77d339040fb90",
    "type": "split",
    "children": [
      {
        "id": "7e38d014ebc9d317",
        "type": "tabs",
        "children": [
          {
            "id": "bbdc93eae0f12ae8",
            "type": "leaf",
            "state": {
              "type": "backlink",
              "state": {
                "collapseAll": false,
                "extraContext": false,
                "sortOrder": "alphabetical",
                "showSearch": false,
                "searchQuery": "",
                "backlinkCollapsed": false,
                "unlinkedCollapsed": true
              },
              "icon": "links-coming-in",
              "title": "Backlinks"
            }
          },
          {
            "id": "d7816399176217c8",
            "type": "leaf",
            "state": {
              "type": "outgoing-link",
              "state": {
                "file": "CSharp/Listas.md",
                "linksCollapsed": false,
                "unlinkedCollapsed": true
              },
              "icon": "links-going-out",
              "title": "Links de saída para Listas"
            }
          },
          {
            "id": "fdf533ad14357f01",
            "type": "leaf",
            "state": {
              "type": "tag",
              "state": {
                "sortOrder": "frequency",
                "useHierarchy": true
              },
              "icon": "lucide-tags",
              "title": "Tags"
            }
          },
          {
            "id": "b370f490b1b6304f",
            "type": "leaf",
            "state": {
              "type": "outline",
              "state": {
                "file": "Node/Entendendo o protocolo HTTP.md",
                "followCursor": false,
                "showSearch": false,
                "searchQuery": ""
              },
              "icon": "lucide-list",
              "title": "Sumário de Entendendo o protocolo HTTP"
            }
          }
        ],
        "currentTab": 3
      }
    ],
    "direction": "horizontal",
    "width": 300,
    "collapsed": true
  },
  "left-ribbon": {
    "hiddenItems": {
      "switcher:Abrir a troca rápida": false,
      "graph:Abrir visualização em gráfico": false,
      "canvas:Criar novo canvas": false,
      "daily-notes:Abrir a nota de hoje": false,
      "templates:Inserir modelo": false,
      "command-palette:Abrir paleta de comandos": false
    }
  },
  "active": "7c01c466821cbbb0",
  "lastOpenFiles": [
    "Udemy/Java Completo - Nelio Alves/Processamento de dados em Java Casting.md",
    "Sumários/Sumário Udemy.md",
    "Udemy/Java Completo - Nelio Alves/Saída de dados em Java.md",
    "Udemy/Java Completo - Nelio Alves/As três operações básicas de programação.md",
    "Udemy/Java Completo - Nelio Alves/Variáveis e tipos básicos em Java.md",
    "Udemy/Java Completo - Nelio Alves/Expressões Aritméticas.md",
    "Udemy/Java Completo - Nelio Alves",
    "Escolas.md",
    "Java/Sintaxe e Semântica.md",
    "Sumários/Sumário Rocketseat.md",
    "Node/Caso de uso de criação de academia.md",
    "Node/Validando distância do check-in.md",
    "Node/Validando data do check-in.md",
    "Projetos/Rocketseat/Api de Restaurante/Criando a estrutura do projeto.md",
    "Sumários/DIO.md",
    "Dio/WEX/Usando a classe.md",
    "Dio/WEX/Usando namespaces.md",
    "Dio/WEX/Criando nossa classe no código.md",
    "Dio/WEX/O conceito de classe.md",
    "Dio/WEX/Criando Projeto.md",
    "CSharp/Função do AppSettings.json.md",
    "CSharp/Lendo o AppSetings.json.md",
    "CSharp/Criando um projeto de API.md",
    "CSharp/O arquivo Program.cs.md",
    "CSharp/Properties.md",
    "CSharp/CLI do .NET.md",
    "Dio/WEX",
    "Dio",
    "Java/Encapsulamento, impedindo acessos diretos.md",
    "Go",
    "Imagens/Pasted image 20250103164210.png",
    "TailwindCSS",
    "Projetos/Rocketseat/Projeto - Adivinhe",
    "React",
    "Imagens/Pasted image 20250329223208.png",
    "Imagens/Pasted image 20250329223056.png",
    "Imagens/Pasted image 20250329223008.png",
    "Imagens/Pasted image 20250329222820.png",
    "Imagens/Pasted image 20250329222554.png",
    "Imagens/Pasted image 20250329222358.png",
    "Imagens/Pasted image 20250329222238.png",
    "Projetos/Rocketseat/Api - Refund",
    "TypeScript",
    "Faculdade/Imagens/Pasted image 20250325214140.png",
    "Faculdade/Imagens/Pasted image 20250325214454.png",
    "Projetos/Rocketseat/Projeto - Hair Day",
    "CSharp/Sem título.canvas"
  ]
}